Metadata-Version: 2.1
Name: xbos-services-utils2
Version: 0.0.6.dev1
Summary: Utility functions for xbos services using Python 2.7.
Home-page: UNKNOWN
Author: Daniel Lengyel
Author-email: daniel.lengyel@berkeley.edu
License: UNKNOWN
Platform: UNKNOWN
